near_synonym/__init__.py
near_synonym/mlm_antonym.py
near_synonym/neg_antonym.py
near_synonym/nli_ernie_lm.py
near_synonym/nli_ernie_tc.py
near_synonym/roformer.py
near_synonym/search.py
near_synonym/tools.py
near_synonym/version.py
tet/__init__.py
tet/tet_ann_alg_of_hnsw.py
tet/tet_calcul_similarity.py
tet/tet_mlm_antonym.py
tet/tet_near_synonym.py
near_synonym-0.3.0.dist-info/LICENSE
near_synonym-0.3.0.dist-info/METADATA
near_synonym-0.3.0.dist-info/WHEEL
near_synonym-0.3.0.dist-info/top_level.txt
near_synonym-0.3.0.dist-info/RECORD
