Metadata-Version: 2.1
Name: near-synonym
Version: 0.3.0
Summary: near-synonym, 中文反义词/近义词(antonym/synonym)工具包.
Home-page: https://github.com/yongzhuo/near-synonym
Author: yongzhuo
Author-email: 1903865025@qq.com
License: MIT
Platform: UNKNOWN
Classifier: License :: OSI Approved :: MIT License
Classifier: Programming Language :: Python :: 3.5
Classifier: Programming Language :: Python :: 3.6
Classifier: Programming Language :: Python :: 3.7
Classifier: Programming Language :: Python :: 3.8
Classifier: Programming Language :: Python :: 3.9
Classifier: Programming Language :: Python :: 3.10
Classifier: Programming Language :: Python :: 3.11
Classifier: Programming Language :: Python :: Implementation :: CPython
Classifier: Programming Language :: Python :: Implementation :: PyPy
License-File: LICENSE
Requires-Dist: huggingface-hub (>=0.20.3)
Requires-Dist: onnxruntime-gpu (==1.12.1)
Requires-Dist: transformers (>=4.30.2)
Requires-Dist: smart-open (>=4.2.0)
Requires-Dist: annoy (>=1.17.3)
